{"nodes": [{"id": "sametreelayout", "label": "SameTreeLayout.tsx", "file_type": "code", "source_file": "C:\\Coding\\Naveen\\Personal\\Github\\Tree\\frontend\\src\\features\\sametree\\components\\SameTreeLayout.tsx", "source_location": "L1"}], "edges": [{"source": "sametreelayout", "target": "dynamic", "relation": "imports_from", "confidence": "EXTRACTED", "source_file": "C:\\Coding\\Naveen\\Personal\\Github\\Tree\\frontend\\src\\features\\sametree\\components\\SameTreeLayout.tsx", "source_location": "L3", "weight": 1.0}, {"source": "sametreelayout", "target": "react", "relation": "imports_from", "confidence": "EXTRACTED", "source_file": "C:\\Coding\\Naveen\\Personal\\Github\\Tree\\frontend\\src\\features\\sametree\\components\\SameTreeLayout.tsx", "source_location": "L4", "weight": 1.0}, {"source": "sametreelayout", "target": "traversalshell", "relation": "imports_from", "confidence": "EXTRACTED", "source_file": "C:\\Coding\\Naveen\\Personal\\Github\\Tree\\frontend\\src\\features\\sametree\\components\\SameTreeLayout.tsx", "source_location": "L5", "weight": 1.0}, {"source": "sametreelayout", "target": "unifiedcontrolsbar", "relation": "imports_from", "confidence": "EXTRACTED", "source_file": "C:\\Coding\\Naveen\\Personal\\Github\\Tree\\frontend\\src\\features\\sametree\\components\\SameTreeLayout.tsx", "source_location": "L6", "weight": 1.0}, {"source": "sametreelayout", "target": "codepanel", "relation": "imports_from", "confidence": "EXTRACTED", "source_file": "C:\\Coding\\Naveen\\Personal\\Github\\Tree\\frontend\\src\\features\\sametree\\components\\SameTreeLayout.tsx", "source_location": "L8", "weight": 1.0}, {"source": "sametreelayout", "target": "explanationpanel", "relation": "imports_from", "confidence": "EXTRACTED", "source_file": "C:\\Coding\\Naveen\\Personal\\Github\\Tree\\frontend\\src\\features\\sametree\\components\\SameTreeLayout.tsx", "source_location": "L9", "weight": 1.0}, {"source": "sametreelayout", "target": "resultpanel", "relation": "imports_from", "confidence": "EXTRACTED", "source_file": "C:\\Coding\\Naveen\\Personal\\Github\\Tree\\frontend\\src\\features\\sametree\\components\\SameTreeLayout.tsx", "source_location": "L10", "weight": 1.0}, {"source": "sametreelayout", "target": "treepanel", "relation": "imports_from", "confidence": "EXTRACTED", "source_file": "C:\\Coding\\Naveen\\Personal\\Github\\Tree\\frontend\\src\\features\\sametree\\components\\SameTreeLayout.tsx", "source_location": "L11", "weight": 1.0}, {"source": "sametreelayout", "target": "usesametreetraversal", "relation": "imports_from", "confidence": "EXTRACTED", "source_file": "C:\\Coding\\Naveen\\Personal\\Github\\Tree\\frontend\\src\\features\\sametree\\components\\SameTreeLayout.tsx", "source_location": "L12", "weight": 1.0}, {"source": "sametreelayout", "target": "selectors", "relation": "imports_from", "confidence": "EXTRACTED", "source_file": "C:\\Coding\\Naveen\\Personal\\Github\\Tree\\frontend\\src\\features\\sametree\\components\\SameTreeLayout.tsx", "source_location": "L13", "weight": 1.0}]}